<?xml version="1.0" encoding="UTF-8"?>
<objects serializationModel="Studio.02.02.00">
	<object class="EncodingSetting" id="{99fa181d-8884-477f-ba3c-0d5378ab63df}">
		<property name="encodingFormat">
			<value>3</value>
		</property>
		<property name="quality">
			<value>37</value>
		</property>
		<relationship name="platform">
			<destination>{a175d86f-b706-4835-974d-0e6a297834e1}</destination>
		</relationship>
		<relationship name="encodable">
			<destination>{a175d86f-b706-4835-974d-0e6a297834e1}</destination>
		</relationship>
	</object>
</objects>
